{
    "name": "Goblin of ETH",
    "description": "Master Stage",
    "image": "https://i.seadn.io/s/raw/files/e2445ea4f3d079b248f94f6b338dd9ce.png?auto=format&dpr=1&w=384",
    "attributes": [
        {
            "trait-type": "Strength",
            "value": 13    
        },
        {
            "trait-type": "Agility",
            "value": 12
        },
        {
            "trait-type": "Magic",
            "value":11
        },
        {
            "trait-type": "Intelligence",
            "value":11
        }
    ]
}